zdtwriter/__init__.py
zdoom_textures_tool-1.0.dist-info/LICENSE
zdoom_textures_tool-1.0.dist-info/METADATA
zdoom_textures_tool-1.0.dist-info/WHEEL
zdoom_textures_tool-1.0.dist-info/top_level.txt
zdoom_textures_tool-1.0.dist-info/RECORD
