Metadata-Version: 2.1
Name: zdoom-textures-tool
Version: 1.0
Summary: Small tool to write a valid textures text file for the zdoom engine, inteded to be used for automated scripts.
Home-page: https://github.com/GianptDev/zdoom-textures-writer
Author: GianptDev
Author-email: gianptdev@gmail.com
License: UNKNOWN
Project-URL: Bug Tracker, https://github.com/GianptDev/zdoom-textures-writer/issues
Platform: UNKNOWN
Classifier: Programming Language :: Python :: 3
Classifier: License :: OSI Approved :: MIT License
Classifier: Operating System :: OS Independent
Classifier: Development Status :: 7 - Inactive
Requires-Python: >=3.6
License-File: LICENSE
